setup.py
uiperf3.py
uiperf3.egg-info/PKG-INFO
uiperf3.egg-info/SOURCES.txt
uiperf3.egg-info/dependency_links.txt
uiperf3.egg-info/top_level.txt