Metadata-Version: 1.1
Name: uiperf3
Version: 0.1.2
Summary: Pure Python, iperf3-compatible network performance test tool.
Home-page: https://micropython.org
Author: Damien George
Author-email: damien.p.george@gmail.com
License: UNKNOWN
Platform: UNKNOWN
Classifier: Programming Language :: Python :: 3
Classifier: License :: OSI Approved :: MIT License
Classifier: Operating System :: OS Independent
